[{"name": "Aruba", "value": 4260}, {"name": "Antigua and Barb.", "value": 13922}, {"name": "United Arab Emirates", "value": 234822}, {"name": "Afghanistan", "value": 889136}, {"name": "Algeria", "value": 952644}, {"name": "Azerbaijan", "value": 1079150}, {"name": "Albania", "value": 1120792}, {"name": "Armenia", "value": 1303148}, {"name": "Andorra", "value": 1304841}, {"name": "Angola", "value": 1349679}, {"name": "American Samoa", "value": 1352578}, {"name": "Argentina", "value": 1461669}, {"name": "Australia", "value": 3181849}, {"name": "Austria", "value": 3349603}, {"name": "Anguilla", "value": 3352415}, {"name": "Antarctica", "value": 3360537}, {"name": "Bahrain", "value": 3436521}, {"name": "Barbados", "value": 3464754}, {"name": "Botswana", "value": 3511128}, {"name": "Bermuda", "value": 3533422}, {"name": "Belgium", "value": 3756597}, {"name": "Bahamas", "value": 3839277}, {"name": "Bangladesh", "value": 4195169}, {"name": "Belize", "value": 4231436}, {"name": "Bosnia and Herz.", "value": 4255196}, {"name": "Bolivia", "value": 4288745}, {"name": "Burma", "value": 4435636}, {"name": "Benin", "value": 4466082}, {"name": "Belarus", "value": 4580877}, {"name": "Solomon Is.", "value": 4590553}, {"name": "Brazil", "value": 4779779}, {"name": "Bhutan", "value": 4801072}, {"name": "Bulgaria", "value": 4900954}, {"name": "Bouvet Is.", "value": 4900966}, {"name": "Brunei", "value": 4960147}, {"name": "Burundi", "value": 5040385}, {"name": "Canada", "value": 6483565}, {"name": "Cambodia", "value": 6596802}, {"name": "Chad", "value": 6667897}, {"name": "Sri Lanka", "value": 6964976}, {"name": "Congo", "value": 7006770}, {"name": "Dem. Rep. Congo", "value": 7025663}, {"name": "China", "value": 8734302}, {"name": "Chile", "value": 8815361}, {"name": "Cayman Is.", "value": 8830847}, {"name": "Cameroon", "value": 8901083}, {"name": "Comoros", "value": 8902470}, {"name": "Colombia", "value": 9009834}, {"name": "N. Mariana Is.", "value": 9010278}, {"name": "Coral Sea Is.", "value": 9010279}, {"name": "Costa Rica", "value": 9042136}, {"name": "Central African Rep.", "value": 9084511}, {"name": "Cuba", "value": 9369392}, {"name": "Cape Verde", "value": 9371805}, {"name": "Cook Is.", "value": 9378676}, {"name": "Cyprus", "value": 9452077}, {"name": "Denmark", "value": 9558215}, {"name": "Djibouti", "value": 9586909}, {"name": "Dominica", "value": 9594100}, {"name": "Jarvis Is.", "value": 9594112}, {"name": "Dominican Rep.", "value": 9625406}, {"name": "Ecuador", "value": 9676399}, {"name": "Egypt", "value": 10269596}, {"name": "Ireland", "value": 10780319}, {"name": "Eq. Guinea", "value": 10786477}, {"name": "Estonia", "value": 10821011}, {"name": "Eritrea", "value": 10847153}, {"name": "El Salvador", "value": 10880404}, {"name": "Ethiopia", "value": 11016395}, {"name": "Czech Rep.", "value": 11103571}, {"name": "French Guiana", "value": 11104697}, {"name": "Finland", "value": 11165144}, {"name": "Fiji", "value": 11232603}, {"name": "Falkland Is.", "value": 11232888}, {"name": "Micronesia", "value": 11236296}, {"name": "Faeroe Is.", "value": 11237758}, {"name": "Fr. Polynesia", "value": 11239522}, {"name": "Baker Is.", "value": 11239528}, {"name": "France", "value": 12470541}, {"name": "Gambia", "value": 12523612}, {"name": "Gabon", "value": 12529936}, {"name": "Georgia", "value": 12567550}, {"name": "Ghana", "value": 12847420}, {"name": "Gibraltar", "value": 12857716}, {"name": "Grenada", "value": 12869934}, {"name": "Guernsey", "value": 12879586}, {"name": "Greenland", "value": 12888672}, {"name": "Germany", "value": 13774514}, {"name": "Guadeloupe", "value": 13775562}, {"name": "Guam", "value": 13805381}, {"name": "Greece", "value": 14301124}, {"name": "Guatemala", "value": 14347491}, {"name": "Guinea", "value": 14376428}, {"name": "Guyana", "value": 14435133}, {"name": "Gaza Strip", "value": 14461140}, {"name": "Haiti", "value": 14529075}, {"name": "Hong Kong", "value": 14622637}, {"name": "Honduras", "value": 14649812}, {"name": "Howland Is.", "value": 14649966}, {"name": "Croatia", "value": 14711009}, {"name": "Hungary", "value": 14851627}, {"name": "Iceland", "value": 14883758}, {"name": "Indonesia", "value": 15292967}, {"name": "Isle of Man", "value": 15293682}, {"name": "India", "value": 17809670}, {"name": "Br. Indian Ocean Ter.", "value": 17809955}, {"name": "Clipperton Is.", "value": 17809961}, {"name": "Iran", "value": 18877131}, {"name": "Israel", "value": 20263482}, {"name": "Italy", "value": 20755227}, {"name": "C\u00c3\u00b4te d'Ivoire", "value": 20777055}, {"name": "Iraq", "value": 21562725}, {"name": "Japan", "value": 22207368}, {"name": "Jersey", "value": 22276914}, {"name": "Jamaica", "value": 22386604}, {"name": "Jan Mayen", "value": 22386608}, {"name": "Jordan", "value": 22610332}, {"name": "Johnston Atoll", "value": 22610362}, {"name": "Kenya", "value": 22994495}, {"name": "Kyrgyzstan", "value": 23040634}, {"name": "Dem. Rep. Korea", "value": 23183373}, {"name": "Kingman Reef", "value": 23183381}, {"name": "Kiribati", "value": 23188099}, {"name": "Korea", "value": 23501491}, {"name": "Christmas Is.d", "value": 23504119}, {"name": "Kuwait", "value": 23598308}, {"name": "Kosovo", "value": 23622203}, {"name": "Kazakhstan", "value": 23683872}, {"name": "Lao PDR", "value": 23709580}, {"name": "Lebanon", "value": 23953692}, {"name": "Latvia", "value": 23993801}, {"name": "Lithuania", "value": 24036074}, {"name": "Liberia", "value": 24127427}, {"name": "Slovakia", "value": 24151701}, {"name": "Palmyra Atoll", "value": 24151710}, {"name": "Liechtenstein", "value": 24153457}, {"name": "Lesotho", "value": 24172538}, {"name": "Luxembourg", "value": 24209951}, {"name": "Libya", "value": 24442278}, {"name": "Madagascar", "value": 24454106}, {"name": "Martinique", "value": 24455447}, {"name": "Macau", "value": 24463453}, {"name": "Moldova", "value": 24485886}, {"name": "Mayotte", "value": 24486138}, {"name": "Mongolia", "value": 24514092}, {"name": "Montserrat", "value": 24515895}, {"name": "Malawi", "value": 24572382}, {"name": "Montenegro", "value": 24580060}, {"name": "North Macedonia", "value": 24630835}, {"name": "Mali", "value": 24694562}, {"name": "Monaco", "value": 24706064}, {"name": "Morocco", "value": 24785609}, {"name": "Mauritius", "value": 24800521}, {"name": "Midway Is.", "value": 24800538}, {"name": "Mauritania", "value": 24811231}, {"name": "Malta", "value": 24894737}, {"name": "Oman", "value": 24952173}, {"name": "Maldives", "value": 24986750}, {"name": "Mexico", "value": 25386959}, {"name": "Malaysia", "value": 25901512}, {"name": "Mozambique", "value": 25941130}, {"name": "New Caledonia", "value": 25943076}, {"name": "Niue", "value": 25943744}, {"name": "Norfolk Is.", "value": 25944157}, {"name": "Niger", "value": 25998858}, {"name": "Vanuatu", "value": 26011459}, {"name": "Nigeria", "value": 27593267}, {"name": "Netherlands", "value": 27810501}, {"name": "Norway", "value": 27930078}, {"name": "Nepal", "value": 28153333}, {"name": "Nauru", "value": 28165502}, {"name": "Suriname", "value": 28169460}, {"name": "Nicaragua", "value": 28190990}, {"name": "New Zealand", "value": 28545403}, {"name": "S. Sudan", "value": 28637804}, {"name": "Paraguay", "value": 28692285}, {"name": "Pitcairn Is.", "value": 28692990}, {"name": "Peru", "value": 28778554}, {"name": "Paracel Is.", "value": 28778764}, {"name": "Spratly Is.", "value": 28780484}, {"name": "Pakistan", "value": 30076096}, {"name": "Poland", "value": 30232414}, {"name": "Panama", "value": 30283088}, {"name": "Portugal", "value": 30352212}, {"name": "Papua New Guinea", "value": 30379810}, {"name": "Palau", "value": 30383786}, {"name": "Guinea-Bissau", "value": 30388667}, {"name": "Qatar", "value": 30519336}, {"name": "R\u00e9union", "value": 30579774}, {"name": "Serbia", "value": 30637340}, {"name": "Marshall Is.", "value": 30643951}, {"name": "Saint Martin", "value": 30644622}, {"name": "Romania", "value": 30738874}, {"name": "Philippines", "value": 31490100}, {"name": "Puerto Rico", "value": 31521949}, {"name": "Russia", "value": 32934290}, {"name": "Rwanda", "value": 33028703}, {"name": "Saudi Arabia", "value": 33611285}, {"name": "St. Pierre and Miquelon", "value": 33611380}, {"name": "Saint Kitts and Nevis", "value": 33614698}, {"name": "Seychelles", "value": 33632897}, {"name": "South Africa", "value": 34344102}, {"name": "Senegal", "value": 34375555}, {"name": "Saint Helena, Ascension, and Tristan da Cunha", "value": 34376010}, {"name": "Slovenia", "value": 34399227}, {"name": "Sierra Leone", "value": 34455380}, {"name": "San Marino", "value": 34456471}, {"name": "Singapore", "value": 34667496}, {"name": "Somalia", "value": 34854901}, {"name": "Spain", "value": 35187343}, {"name": "Saint Lucia", "value": 35194344}, {"name": "Sudan", "value": 35399086}, {"name": "Svalbard", "value": 35401178}, {"name": "Sweden", "value": 35574931}, {"name": "Syria", "value": 36845227}, {"name": "Switzerland", "value": 37098107}, {"name": "Trinidad and Tobago", "value": 37160855}, {"name": "Tromelin Is.", "value": 37160857}, {"name": "Thailand", "value": 37474767}, {"name": "Tajikistan", "value": 37526157}, {"name": "Turks and Caicos Is.", "value": 37526404}, {"name": "Tokelau", "value": 37526998}, {"name": "Tonga", "value": 37535446}, {"name": "Togo", "value": 37543960}, {"name": "S\u00c3\u00a3o Tom\u00c3\u00a9 and Principe", "value": 37544856}, {"name": "Tunisia", "value": 37652613}, {"name": "Timor-Leste", "value": 37660984}, {"name": "Turkey", "value": 38598416}, {"name": "Tuvalu", "value": 38601652}, {"name": "Taiwan", "value": 38739613}, {"name": "Turkmenistan", "value": 38776678}, {"name": "Tanzania", "value": 38872230}, {"name": "Uganda", "value": 39061629}, {"name": "United Kingdom", "value": 41917129}, {"name": "Ukraine", "value": 42390073}, {"name": "United States", "value": 62876187}, {"name": "Burkina Faso", "value": 62901327}, {"name": "Uruguay", "value": 62918005}, {"name": "Uzbekistan", "value": 62963308}, {"name": "St. Vin. and Gren.", "value": 62968028}, {"name": "Venezuela", "value": 63081265}, {"name": "British Virgin Is.", "value": 63083867}, {"name": "Vietnam", "value": 63390502}, {"name": "U. S. Virgin Is.", "value": 63395467}, {"name": "Vatican City", "value": 63418717}, {"name": "Namibia", "value": 63487791}, {"name": "West Bank", "value": 63593096}, {"name": "Wallis and Futuna", "value": 63593102}, {"name": "Wake Island", "value": 63599294}, {"name": "Samoa", "value": 63619601}, {"name": "Eswatini", "value": 63639146}, {"name": "Yemen", "value": 63987686}, {"name": "Zambia", "value": 64097251}, {"name": "Zimbabwe", "value": 64347879}]